app_auth/__init__.py
app_auth/admin.py
app_auth/apps.py
app_auth/auth_settings.py
app_auth/migrations/.gitkeep
app_auth/models.py
app_auth/oidc_backend.py
app_auth/templates/base.html
app_auth/tests.py
app_auth/urls.py
app_auth/user_serializers.py
app_auth/views.py
app_auth-0.1.0.dist-info/METADATA
app_auth-0.1.0.dist-info/WHEEL
app_auth-0.1.0.dist-info/RECORD
